ctis/__init__.py
ctis-0.0.0.dist-info/METADATA
ctis-0.0.0.dist-info/WHEEL
ctis-0.0.0.dist-info/top_level.txt
ctis-0.0.0.dist-info/RECORD
